topsis/__init__.py
topsis/topsis.py
topsis_navneet_102203715-1.0.3.dist-info/METADATA
topsis_navneet_102203715-1.0.3.dist-info/WHEEL
topsis_navneet_102203715-1.0.3.dist-info/entry_points.txt
topsis_navneet_102203715-1.0.3.dist-info/top_level.txt
topsis_navneet_102203715-1.0.3.dist-info/RECORD
