Metadata-Version: 2.1
Name: topsis_navneet_102203715
Version: 1.0.3
Summary: A Python package to perform TOPSIS (Technique for Order Preference by Similarity to Ideal Solution)
Home-page: https://github.com/sagar09navneet/topsis_navneet_10203715
Author: Navneet Sagar
Author-email: sagar.26navneet@gmail.com
Classifier: Programming Language :: Python :: 3
Classifier: License :: OSI Approved :: MIT License
Classifier: Operating System :: OS Independent
Requires-Python: >=3.6
Requires-Dist: numpy
Requires-Dist: pandas
